mmcrypto/Crypto.py
mmcrypto/Signals.py
mmcrypto/_Price.py
mmcrypto/__all__.py
mmcrypto/__init__.py
mmcrypto-0.0.7.dist-info/METADATA
mmcrypto-0.0.7.dist-info/WHEEL
mmcrypto-0.0.7.dist-info/top_level.txt
mmcrypto-0.0.7.dist-info/RECORD
