Metadata-Version: 2.1
Name: mmcrypto
Version: 0.0.7
Summary: Downloads, save and retrieve cryptocoins data from wazirx
Home-page: https://github.com/manasm11/mmcrypto
Author: Manas Mishra
Author-email: manas.m22@gmail.com
License: UNKNOWN
Platform: UNKNOWN
Classifier: Programming Language :: Python :: 3
Classifier: License :: OSI Approved :: MIT License
Classifier: Operating System :: POSIX :: Linux
Requires-Python: >=3.7
Requires-Dist: requests (==2.21.0)
